<!DOCTYPE ui:UiBinder SYSTEM "http://dl.google.com/gwt/DTD/xhtml.ent">
<ui:UiBinder xmlns:ui="urn:ui:com.google.gwt.uibinder" xmlns:g="urn:import:com.google.gwt.user.client.ui" xmlns:f="urn:import:org.exoplatform.gwtframework.ui.client.component"
   xmlns:s="urn:import:org.exoplatform.ide.extension.heroku.client.stack">
   <ui:with field='resource' type='org.exoplatform.ide.extension.heroku.client.HerokuClientBundle' />
   <ui:with field="locale" type="org.exoplatform.ide.extension.heroku.client.HerokuLocalizationConstant"></ui:with>
   <f:VPanel>
      <f:Border margin="10">
         <s:StackGrid width="100%" ui:field="stackGrid"></s:StackGrid>
      </f:Border>
      <g:HorizontalPanel height="40" spacing="5" horizontalAlignment="center" verticalAlignment="middle">
         <g:cell horizontalAlignment="right">
            <f:ImageButton ui:field="changeButton" width="90" height="22" text="{locale.changeButton}" imageResource="{resource.okButton}"
               disabledImageResource="{resource.okButtonDisabled}"></f:ImageButton>
         </g:cell>
         <g:cell horizontalAlignment="left">
            <f:ImageButton ui:field="cancelButton" width="90" height="22" text="{locale.cancelButton}" imageResource="{resource.cancelButton}"
               disabledImageResource="{resource.cancelButtonDisabled}"></f:ImageButton>
         </g:cell>
      </g:HorizontalPanel>
   </f:VPanel>
</ui:UiBinder> 
