<!--

    Copyright (c) 2012-2014 Codenvy, S.A.
    All rights reserved. This program and the accompanying materials
    are made available under the terms of the Eclipse Public License v1.0
    which accompanies this distribution, and is available at
    http://www.eclipse.org/legal/epl-v10.html

    Contributors:
      Codenvy, S.A. - initial API and implementation

-->
<ui:UiBinder xmlns:ui='urn:ui:com.google.gwt.uibinder'
             xmlns:g='urn:import:com.google.gwt.user.client.ui'>
    <ui:with field='res' type='com.codenvy.ide.Resources'/>
    <ui:with field='locale' type='com.codenvy.ide.CoreLocalizationConstant'/>
    <ui:with field='wizardResources' type='com.codenvy.ide.wizard.project.ProjectWizardResources'/>
    <ui:style src="com/codenvy/ide/api/ui/style.css" type="com.codenvy.ide.wizard.project.ProjectWizardViewImpl.Style">
        @eval bgTopPanel com.codenvy.ide.api.theme.Style.getConsolePanelColor();
        .project {
            /*margin-right: 8px;*/
            margin-top: 4px;
            margin-left: 5px;
        }

        .projectNamePosition {
            position: relative;
            line-height: 29px;
            margin-left: 9px;
            font-weight: 700;
            float: left;
            font-size: 12px;
        }

        .topPanel {
            height: 38px;
            border-top: 1px solid #232323;
            border-bottom: 1px solid #232323;
            z-index: 4;
            background-color: bgTopPanel;
            font-size: 12px;
        }

        .namePanel, .namePanelRight {
            border-right: 1px solid tabBorder;
            box-shadow: 1px 0px 0px 0px tabBorderShadow;
            position: relative;
            top: -1px;
            overflow: hidden;
            display: inline-block;
            /*background-color: dialogContentBackground ;*/

        }

        .namePanelRight {
            border-right: none;
            box-shadow: 0px 0px 0 0 tabBorderShadow;
        }

        .rootPanel {
            position: relative;
            text-shadow: 0 1px 0 rgba(0, 0, 0, 0.5);
        }

        .privacy {
            display: inline-block;
            margin-top: 8px;
            margin-left: 5px;
        }

        .privacy label {
            padding-left: 17px;
        }

        .tab {
            left: 0px;
            top: 0px;
            right: 0px;
            bottom: 0px;
            position: absolute !important;
        }

        .buttonLikePanelLeft, .buttonLikePanelRight {
            cursor: pointer;
            background-color: toolbarBackgroundColor;
            width: 26px;
            position: absolute;
        }

        .centerPanel {
            position: relative;
            box-shadow: 0 -1px 0 0 tabBorder;
        }

        .svgStyle, .svgRotated {
            width: 26px;
            height: 24px;
            position: relative;
            top: 200px;
        }

        .disabled {
            /* opacity now done in button/blueButton[disabled] in the text color and background */
            /* opacity: 0.35; */
        }

        .labelPanel {
            float: left;
            display: block;
            font-size: 11px;
        }

        .labelPanelLeft {
            float: left;
            display: block;
            font-size: 11px;
            width: 190px;
            overflow: hidden;
        }

        .labelPanelRight {
            float: left;
            display: block;
            font-size: 11px;
            overflow: hidden;
        }

        .labelPanel > div {
            margin-top: 4px;
        }

        .infoText {
            margin-left: 10px;
        }

        .infoText a {
            color: #66CD00;
            top: 4px;
            position: relative;
        }

        .infoText a:hover {
            color: #7FFF00;
        }

        .infoTextLine1 {
            line-height: 18px;
            height: 18px;
        }

        .infoTextLine2 {
            line-height: 10px;
            height: 20px;
        }

        .infoValue {
            margin-left: 2px;
            margin-right: 20px;
        }

        .visible {
            visibility: visible;
        }

        .hidden {
            visibility: hidden;
        }

        .grayColor {
            color: #818181;
        }
    </ui:style>
    <g:FlowPanel width="774px" height="550px" addStyleNames="{style.rootPanel}">
        <g:FlowPanel width="774px" height="470px" addStyleNames="{style.centerPanel}">
            <g:SimplePanel ui:field="wizardPanel" addStyleNames="{style.tab}"/>
        </g:FlowPanel>
        <g:FlowPanel addStyleNames="{style.topPanel} {style.grayColor}" height="40px">
            <g:FlowPanel addStyleNames="{style.labelPanelLeft}" height="40px" width="190px">
                <g:Label ui:field="builderEnvConfText" text="Builder Environment Configuration :"
                         addStyleNames="{style.infoText} {style.infoTextLine1}"/>
                <g:Label ui:field="runnerEnvConfText" text="Runner Environment Configuration :"
                         addStyleNames="{style.infoText} {style.infoTextLine2}"/>
            </g:FlowPanel>
            <g:FlowPanel addStyleNames="{style.labelPanelRight}" height="40px" width="580px">
                <g:Label ui:field="builderEnvConf" addStyleNames="{style.infoTextLine1}"/>
                <g:Label ui:field="runnerEnvConf" addStyleNames="{style.infoTextLine2}"/>
            </g:FlowPanel>
        </g:FlowPanel>
        <g:FlowPanel addStyleNames="{wizardResources.css.buttonPanel}">
            <g:Button ui:field="saveButton" addStyleNames="{wizardResources.css.blueButton}" tabIndex="5"
                      debugId="projectWizard-saveButton"/>
            <g:Button ui:field="nextStepButton" text="Next" addStyleNames="{wizardResources.css.button}" tabIndex="6"
                      debugId="projectWizard-nextStepButton"/>
            <g:Button ui:field="previousStepButton" text="Previous" addStyleNames="{wizardResources.css.button}" tabIndex="7"
                      debugId="projectWizard-previousStepButton"/>
            <g:FlowPanel ui:field="infoRAMPanel" addStyleNames="{style.hidden}">
                <g:FlowPanel addStyleNames="{style.labelPanel}">
                    <g:Label text="RAM Required:" addStyleNames="{style.infoText}"/>
                </g:FlowPanel>
                <g:FlowPanel addStyleNames="{style.labelPanel}">
                    <g:Label ui:field="requiredRAM" addStyleNames="{style.infoValue}"/>
                </g:FlowPanel>
                <g:FlowPanel addStyleNames="{style.labelPanel}">
                    <g:Label text="RAM Available:" addStyleNames="{style.infoText}"/>
                </g:FlowPanel>
                <g:FlowPanel addStyleNames="{style.labelPanel}">
                    <g:Label ui:field="availableRAM" addStyleNames="{style.infoValue}"/>
                </g:FlowPanel>
                <g:FlowPanel addStyleNames="{style.labelPanel} {style.infoText}">
                    <g:Anchor text="Get More RAM" href="{locale.createProjectFromTemplatelinkGetMoreRAM}" target="_blank"
                              addStyleNames="{style.infoText}"/>
                </g:FlowPanel>
            </g:FlowPanel>
        </g:FlowPanel>
    </g:FlowPanel>
</ui:UiBinder>